odoo/addons/l10n_nl_dutch_company_type/README.rst
odoo/addons/l10n_nl_dutch_company_type/__init__.py
odoo/addons/l10n_nl_dutch_company_type/__manifest__.py
odoo/addons/l10n_nl_dutch_company_type/data/l10n_nl_dutch_company_type.xml
odoo/addons/l10n_nl_dutch_company_type/i18n/l10n_nl_dutch_company_type.pot
odoo/addons/l10n_nl_dutch_company_type/i18n/nl.po
odoo/addons/l10n_nl_dutch_company_type/readme/CONFIGURE.rst
odoo/addons/l10n_nl_dutch_company_type/readme/CONTRIBUTORS.rst
odoo/addons/l10n_nl_dutch_company_type/readme/DESCRIPTION.rst
odoo/addons/l10n_nl_dutch_company_type/readme/INSTALL.rst
odoo/addons/l10n_nl_dutch_company_type/static/description/icon.png
odoo/addons/l10n_nl_dutch_company_type/static/description/index.html
odoo11_addon_l10n_nl_dutch_company_type-11.0.2.0.0.dist-info/METADATA
odoo11_addon_l10n_nl_dutch_company_type-11.0.2.0.0.dist-info/WHEEL
odoo11_addon_l10n_nl_dutch_company_type-11.0.2.0.0.dist-info/top_level.txt
odoo11_addon_l10n_nl_dutch_company_type-11.0.2.0.0.dist-info/RECORD
